animateplot/__init__.py
animateplot/animat_plot.py
animateplot/video/__init__.py
animateplot/video/exceptions_animateplot.py
animateplot/video/video.py
animateplot/video/video_movie.py
animateplot-0.4.10.dist-info/licenses/LICENSE
animateplot-0.4.10.dist-info/METADATA
animateplot-0.4.10.dist-info/WHEEL
animateplot-0.4.10.dist-info/top_level.txt
animateplot-0.4.10.dist-info/RECORD
