Metadata-Version: 2.4
Name: animateplot
Version: 0.4.10
Summary: Library for generate gif or video from plots
Home-page: https://github.com/reinanbr/animatePlot
Author: Reinan Br
Author-email: slimchatuba@gmail.com
License: BSD v3
Keywords: gif video plot
Requires-Python: >=3.8
License-File: LICENSE
Requires-Dist: contourpy==1.3.3
Requires-Dist: cycler==0.12.1
Requires-Dist: decorator==5.2.1
Requires-Dist: fonttools==4.59.2
Requires-Dist: imageio==2.37.0
Requires-Dist: imageio-ffmpeg==0.6.0
Requires-Dist: kiwisolver==1.4.9
Requires-Dist: matplotlib==3.10.6
Requires-Dist: moviepy==2.2.1
Requires-Dist: numpy==2.2.6
Requires-Dist: opencv-python==4.12.0.88
Requires-Dist: packaging==25.0
Requires-Dist: pillow==11.3.0
Requires-Dist: proglog==0.1.12
Requires-Dist: pyparsing==3.2.3
Requires-Dist: python-dateutil==2.9.0.post0
Requires-Dist: python-dotenv==1.1.1
Requires-Dist: six==1.17.0
Requires-Dist: tqdm==4.67.1
Requires-Dist: ipywidgets
Dynamic: author
Dynamic: author-email
Dynamic: description
Dynamic: description-content-type
Dynamic: home-page
Dynamic: keywords
Dynamic: license
Dynamic: license-file
Dynamic: requires-dist
Dynamic: requires-python
Dynamic: summary
